pyo/__init__.py
pyo/_linux_wheel_fix_symlinks.py
pyo/_pyo.cpython-39-darwin.so
pyo/_pyo64.cpython-39-darwin.so
pyo/libFLAC.12.dylib
pyo/liblo.7.dylib
pyo/libmp3lame.0.dylib
pyo/libmpg123.0.dylib
pyo/libogg.0.dylib
pyo/libopus.0.dylib
pyo/libout123.0.dylib
pyo/libportaudio.2.dylib
pyo/libportmidi.2.0.3.dylib
pyo/libsndfile.1.dylib
pyo/libsyn123.0.dylib
pyo/libvorbis.0.dylib
pyo/libvorbisenc.2.dylib
pyo/libvorbisfile.3.dylib
pyo/editor/EPyo.py
pyo/editor/Tutorial_01_RingMod.py
pyo/editor/Tutorial_02_Flanger.py
pyo/editor/Tutorial_03_TriTable.py
pyo/editor/__init__.py
pyo/editor/snippets/__init__.py
pyo/editor/snippets/Audio/SoundPlayer
pyo/editor/snippets/Audio/TableOsc
pyo/editor/snippets/Audio/__init__.py
pyo/editor/snippets/Control/ChorusJit
pyo/editor/snippets/Control/Vibrato
pyo/editor/snippets/Control/__init__.py
pyo/editor/snippets/Interface/NewFrame
pyo/editor/snippets/Interface/PaintPanel
pyo/editor/snippets/Interface/__init__.py
pyo/editor/snippets/Utilities/ChooseAudioDev
pyo/editor/snippets/Utilities/Incrementor
pyo/editor/snippets/Utilities/__init__.py
pyo/editor/styles/Custom
pyo/editor/styles/Default
pyo/editor/styles/Espresso
pyo/editor/styles/Monokai-Soda
pyo/editor/styles/Smooth
pyo/editor/styles/Soft
pyo/editor/styles/Solarized (dark)
pyo/editor/styles/Solarized (light)
pyo/editor/styles/__init__.py
pyo/examples/__init__.py
pyo/examples/01-intro/01-audio-server.py
pyo/examples/01-intro/02-sine-tone.py
pyo/examples/01-intro/03-parallel-proc.py
pyo/examples/01-intro/04-serial-proc.py
pyo/examples/01-intro/05-output-channels.py
pyo/examples/01-intro/__init__.py
pyo/examples/02-controls/01-fixed-control.py
pyo/examples/02-controls/02-dynamic-control.py
pyo/examples/02-controls/03-output-range.py
pyo/examples/02-controls/04-building-lfo.py
pyo/examples/02-controls/05-math-ops.py
pyo/examples/02-controls/06-multichannel-expansion.py
pyo/examples/02-controls/07-multichannel-expansion-2.py
pyo/examples/02-controls/08-handling-channels.py
pyo-1.0.5.dist-info/LICENSE
pyo-1.0.5.dist-info/METADATA
pyo-1.0.5.dist-info/WHEEL
pyo-1.0.5.dist-info/entry_points.txt
pyo-1.0.5.dist-info/top_level.txt
pyo-1.0.5.dist-info/RECORD
