Metadata-Version: 2.1
Name: pyo
Version: 1.0.5
Summary: Python module to build digital signal processing program.
Home-page: http://ajaxsoundstudio.com/software/pyo/
Author: Olivier Belanger
Author-email: belangeo@gmail.com
License: LGPLv3+
Project-URL: Bug Tracker, https://github.com/belangeo/pyo/issues
Project-URL: Documentation, http://ajaxsoundstudio.com/pyodoc/
Project-URL: Source Code, https://github.com/belangeo/pyo
Keywords: audio sound dsp synthesis signal-processing music
Classifier: Development Status :: 5 - Production/Stable
Classifier: Intended Audience :: Developers
Classifier: Intended Audience :: End Users/Desktop
Classifier: Intended Audience :: Science/Research
Classifier: Intended Audience :: Other Audience
Classifier: Operating System :: MacOS :: MacOS X
Classifier: Operating System :: Microsoft :: Windows
Classifier: Operating System :: POSIX :: Linux
Classifier: License :: OSI Approved :: GNU General Public License v3 or later (GPLv3+)
Classifier: Topic :: Multimedia :: Sound/Audio
Classifier: Topic :: Multimedia :: Sound/Audio :: Analysis
Classifier: Topic :: Multimedia :: Sound/Audio :: Capture/Recording
Classifier: Topic :: Multimedia :: Sound/Audio :: Sound Synthesis
Classifier: Programming Language :: Python :: 3
Classifier: Programming Language :: Python :: 3.7
Classifier: Programming Language :: Python :: 3.8
Classifier: Programming Language :: Python :: 3.9
Classifier: Programming Language :: Python :: 3.10
Classifier: Programming Language :: Python :: 3.11
Requires-Python: >=3.7, <4
License-File: LICENSE
